img2tags/__init__.py
img2tags/common.py
img2tags/img2tags.py
img2tags/tagger.py
img2tags-1.6.6.dist-info/METADATA
img2tags-1.6.6.dist-info/WHEEL
img2tags-1.6.6.dist-info/entry_points.txt
img2tags-1.6.6.dist-info/licenses/LICENSE.txt
img2tags-1.6.6.dist-info/RECORD
