Metadata-Version: 2.4
Name: img2tags
Version: 1.6.6
Author-email: yuta@hayashibe.jp
License-Expression: Apache-2.0
License-File: LICENSE.txt
Requires-Python: <4,>=3.10
Requires-Dist: huggingface-hub>=0.25.0
Requires-Dist: numpy>=2.1.1
Requires-Dist: opencv-python>=4.10.0.84
Requires-Dist: pillow>=10.4.0
Requires-Dist: pydantic>=2.9.2
Requires-Dist: rich>=13.8.1
Requires-Dist: torch>=2.4.1
Provides-Extra: cpu
Requires-Dist: onnxruntime>=1.19.2; extra == 'cpu'
Provides-Extra: gpu
Requires-Dist: onnxruntime-gpu>=1.19.2; extra == 'gpu'
